{"trial_id": "0083", "hyperparameters": {"space": [{"class_name": "Int", "config": {"name": "units_1", "default": null, "conditions": [], "min_value": 16, "max_value": 64, "step": 16, "sampling": "linear"}}, {"class_name": "Float", "config": {"name": "dropout_1", "default": 0.2, "conditions": [], "min_value": 0.2, "max_value": 0.9, "step": 0.1, "sampling": "linear"}}, {"class_name": "Int", "config": {"name": "units_2", "default": null, "conditions": [], "min_value": 16, "max_value": 64, "step": 16, "sampling": "linear"}}, {"class_name": "Float", "config": {"name": "dropout_2", "default": 0.2, "conditions": [], "min_value": 0.2, "max_value": 0.9, "step": 0.1, "sampling": "linear"}}, {"class_name": "Choice", "config": {"name": "optimizer", "default": "adam", "conditions": [], "values": ["adam", "adagrad", "adadelta", "nadam", "ftrl"], "ordered": false}}, {"class_name": "Float", "config": {"name": "learning_rate", "default": 0.001, "conditions": [], "min_value": 0.001, "max_value": 0.1, "step": null, "sampling": "log"}}], "values": {"units_1": 16, "dropout_1": 0.6000000000000001, "units_2": 16, "dropout_2": 0.2, "optimizer": "nadam", "learning_rate": 0.0012474684203056348, "tuner/epochs": 40, "tuner/initial_epoch": 14, "tuner/bracket": 1, "tuner/round": 1, "tuner/trial_id": "0080"}}, "metrics": {"metrics": {"loss": {"direction": "min", "observations": [{"value": [0.2663493752479553], "step": 10}]}, "accuracy": {"direction": "max", "observations": [{"value": [0.9295597672462463], "step": 10}]}, "precision": {"direction": "min", "observations": [{"value": [0.8929804563522339], "step": 10}]}, "recall": {"direction": "min", "observations": [{"value": [0.9761006236076355], "step": 10}]}, "auc": {"direction": "min", "observations": [{"value": [0.9739264249801636], "step": 10}]}, "val_loss": {"direction": "min", "observations": [{"value": [0.2779902219772339], "step": 10}]}, "val_accuracy": {"direction": "max", "observations": [{"value": [0.8975609540939331], "step": 10}]}, "val_precision": {"direction": "min", "observations": [{"value": [0.15909090638160706], "step": 10}]}, "val_recall": {"direction": "min", "observations": [{"value": [0.5833333134651184], "step": 10}]}, "val_auc": {"direction": "min", "observations": [{"value": [0.9242043495178223], "step": 10}]}}}, "score": 0.2779902219772339, "best_step": 10, "status": "COMPLETED", "message": null}